Unit/tests.py
Unit/All.py
Unit/Prelude.py
Unit/Functor.py
Unit/__init__.py
Unit.py-1.0.0.dist-info/top_level.txt
Unit.py-1.0.0.dist-info/METADATA
Unit.py-1.0.0.dist-info/DESCRIPTION.rst
Unit.py-1.0.0.dist-info/RECORD
Unit.py-1.0.0.dist-info/WHEEL
Unit.py-1.0.0.dist-info/metadata.json
